Workbook

Sheet INPUT
A1: Clean World Maintenance | F1: Division : | H1: Sales Rep:
A2: UPDATED: 1.30.205 | G2: 1
F3: v-- Copy Below / Paste "123" Above --^
F4: Estimating Department | G4: 1
B9: Project : | C9: Copy/Paste "123" -v | E9: Date :
C10: 2017-1 | D10: =TODAY() -> 46078 | E10: 42874
B11: Company | E11: Office Phone
B13: Street: | E13: Contact:
E14: =F2 -> 0
B15: City & State | E15: Cell Phone
E16: =H2 -> 0
B18: Notes:
B19: We propose to furnish all materials and perform labor necessary to complete
B20: the following cleaning service at Prevailing Wage rate:
B23: Final Cleaning Cost: $
B24: This would be the cleaning of walls, doors, doorframes, lights, fixtures, vacuum,
B25: switches, plug plates, baseboards, cabinets, restrooms, sweep and mop.
B26: _ Final Cleaning Cost: $
B27: This would be the cleaning of walls, doors, doorframes, lights, fixtures, vacuum,
B28: switches, plug plates, baseboards, cabinets, restrooms, sweep and mop.
B29: Floor Cleaning Cost: $
B30: Removal of factory finish and applying 3 coats of wax to VCT flooring.
A31: --->
A32: ---> | B32: General Cleaning Cost: $ 38.50 per worker hour
A33: ---> | B33: General cleanup of work area. Following directions provided by supervisor.
A34: --->
A35: ---> | B35: Elevator Driver Cost: $ 38.50 per worker hour
A36: ---> | B36: English and Spanish speaking elevator driver. Normal work day (M-F)
A37: --->
A38: --->
A39: --->

Sheet NORMAL WAGE
A4: CALCULATIONS PER SQUARE FOOT | B4: Total SQFT | C4: Estimate Cost: | D4: SQFT COST
C5: 0.27 | D5: =+B5*C5 -> 0
A9: COST ESTIMATE | B9: COST | C9: Cost Per Man Hr | D9: Total Hours | E9: Work Day Hours | F9: Total Workers Needed
A10: CLEANING | B10: 0 | C10: 39.5 | D10: =+B10/C10 -> 0 | E10: 9 | F10: =+D10/E10 -> 0
A11: WINDOW WASHING | B11: 0 | C11: 39.5 | D11: =+B11/C11 -> 0 | E11: 9 | F11: =+D11/E11 -> 0
A12: WAXING | B12: 0 | C12: 39.5 | D12: =+B12/C12 -> 0 | E12: 9 | F12: =+D12/E12 -> 0 | H12: ADDRESS:
A13: TRAVEL | B13: 0
A14: LIFT | B14: 0
A15: SUBTOTAL
A16: PARKING | B16: 0 | H16: COMMENTS:
A17: ADD 6% FOR ADDITIONAL COSTS | B17: 0
A18: GRAND TOTAL | B18: =SUM(B10:B17) -> 0
A20: \/ - MORE FLOORS - \/
A22: COST ESTIMATE | B22: COST | C22: Cost Per Man Hr | D22: Total Hours | E22: Work Day Hours | F22: Total Workers Needed
A23: CLEANING | B23: 0 | C23: 39.5 | D23: =+B23/C23 -> 0 | E23: 9 | F23: =+D23/E23 -> 0
A24: WINDOW WASHING | B24: 0 | C24: 39.5 | D24: =+B24/C24 -> 0 | E24: 9 | F24: =+D24/E24 -> 0
A25: WAXING | B25: 0 | C25: 39.5 | D25: =+B25/C25 -> 0 | E25: 9 | F25: =+D25/E25 -> 0
A26: TRAVEL | B26: 0
A27: LIFT | B27: 0
A28: SUBTOTAL
A29: PARKING | B29: 0
A30: ADD 6% FOR ADDITIONAL COSTS | B30: 0
A31: GRAND TOTAL | B31: =SUM(B23:B30) -> 0
A33: COST ESTIMATE | B33: COST | C33: Cost Per Man Hr | D33: Total Hours | E33: Work Day Hours | F33: Total Workers Needed
A34: CLEANING | B34: 0 | C34: 39.5 | D34: =+B34/C34 -> 0 | E34: 9 | F34: =+D34/E34 -> 0
A35: WINDOW WASHING | B35: 0 | C35: 39.5 | D35: =+B35/C35 -> 0 | E35: 9 | F35: =+D35/E35 -> 0
A36: WAXING | B36: 0 | C36: 39.5 | D36: =+B36/C36 -> 0 | E36: 9 | F36: =+D36/E36 -> 0
A37: TRAVEL | B37: 0
A38: LIFT | B38: 0
A39: SUBTOTAL
A40: PARKING | B40: 0
A41: ADD 6% FOR ADDITIONAL COSTS | B41: 0
A42: GRAND TOTAL | B42: =SUM(B34:B41) -> 0
A44: COST ESTIMATE | B44: COST | C44: Cost Per Man Hr | D44: Total Hours | E44: Work Day Hours | F44: Total Workers Needed
A45: CLEANING | B45: 0 | C45: 39.5 | D45: =+B45/C45 -> 0 | E45: 9 | F45: =+D45/E45 -> 0
A46: WINDOW WASHING | B46: 0 | C46: 39.5 | D46: =+B46/C46 -> 0 | E46: 9 | F46: =+D46/E46 -> 0
A47: WAXING | B47: 0 | C47: 39.5 | D47: =+B47/C47 -> 0 | E47: 9 | F47: =+D47/E47 -> 0
A48: TRAVEL | B48: 0
A49: LIFT | B49: 0
A50: SUBTOTAL
A51: PARKING | B51: 0
A52: ADD 6% FOR ADDITIONAL COSTS | B52: 0
A53: GRAND TOTAL | B53: =SUM(B45:B52) -> 0
A55: COST ESTIMATE | B55: COST | C55: Cost Per Man Hr | D55: Total Hours | E55: Work Day Hours | F55: Total Workers Needed
A56: CLEANING | B56: 0 | C56: 39.5 | D56: =+B56/C56 -> 0 | E56: 9 | F56: =+D56/E56 -> 0
A57: WINDOW WASHING | B57: 0 | C57: 39.5 | D57: =+B57/C57 -> 0 | E57: 9 | F57: =+D57/E57 -> 0
A58: WAXING | B58: 0 | C58: 39.5 | D58: =+B58/C58 -> 0 | E58: 9 | F58: =+D58/E58 -> 0
A59: TRAVEL | B59: 0
A60: LIFT | B60: 0
A61: SUBTOTAL
A62: PARKING | B62: 0
A63: ADD 6% FOR ADDITIONAL COSTS | B63: 0
A64: GRAND TOTAL | B64: =SUM(B56:B63) -> 0
A72: REALITY ESTIMATION
B73: Total SQFT
D74: Work Day Hours | E74: Total hours | F74: Price /hour | G74: Total cost | H74: SQFT PRICE
D75: 9 | E75: =+B76*B77*D75 -> 18 | F75: 39.5 | G75: =+E75*F75 -> 711 | H75: =+G75/B74 -> #DIV/0!
A76: Can We Do The Project In X Days -------->>>>>>>>>>> | B76: 1 | C76: DAYS
A77: Can We Do The Project With X Workers -------->>>>> | B77: 2 | C77: WORKERS
A84: WINDOWS | B84: Units
A85: Window Count | C85: 12.5 | D85: =+B85*C85 -> 0
A88: FLOOR WAXING | B88: SqFt
A89: FLOOR | C89: 0.47 | D89: =+B89*C89 -> 0
A91: CARPET - 1st FLOOR ($175 MINIMUM) | B91: SqFt
A92: FLOOR | C92: 0.2 | D92: =+B92*C92 -> 0
A95: CARPET CLEANING | B95: SqFt
A96: FLOOR | C96: 0.13 | D96: =+B96*C96 -> 0
A98: FLOOR WAXING | B98: SqFt
A99: FLOOR | C99: 0.27 | D99: =+B99*C99 -> 0
A102: TRAVEL | B102: Workers | C102: Hours | D102: Cost | E102: Days | F102: Total:
A103: Travel | D103: 15 | F103: =+B103*C103*D103*E103 -> 0
A104: Hotel | D104: 115 | F104: =+B104*C104*D104*E104 -> 0
A105: PARKING | D105: 30 | F105: =+B105*C105*D105*E105 -> 0

Sheet PREVAILING WAGE
N1: PREVAILING WAGE | O1: 1.5.2025 - DATE
A2: CLEANING ($ 727.00 MINIMUM)
O3: WAGE: 40.91 | P3: FRINGE: 17.30
A4: CALCULATIONS PER SQUARE FOOT | B4: Total SQFT | C4: Estimate Cost: | D4: SQFT COST | N4: EMPLOYEE | O4: OFFICE | P4: TOTAL
C5: 0.59 | D5: =+B5*C5 -> 0 | N5: 58.21 | O5: 73.05 | P5: 104.36
N7: PREVAILING WAGE | O7: 7.5.2024 - DATE
A9: COST ESTIMATE | B9: COST | C9: Cost Per Man Hr | D9: Total Hours | E9: Work Day Hours | F9: Total Workers Needed | O9: WAGE: 31.39 | P9: FRINGE: 16.80
A10: CLEANING | B10: 0 | C10: 104.5 | D10: =+B10/C10 -> 0 | E10: 9 | F10: =+D10/E10 -> 0 | N10: EMPLOYEE | O10: OFFICE | P10: TOTAL
A11: WINDOW WASHING | B11: 0 | C11: 104.5 | D11: =+B11/C11 -> 0 | E11: 9 | F11: =+D11/E11 -> 0 | N11: 48.19 | O11: 60.47 | P11: 86.39
A12: WAXING | B12: 0 | C12: 104.5 | D12: =+B12/C12 -> 0 | E12: 9 | F12: =+D12/E12 -> 0 | H12: ADDRESS:
A13: TRAVEL | B13: 0 | N13: WASHINGTON STATE
A14: LIFT | B14: 0 | N14: 11.8.2024 - DATE | O14: WAGE: 50.06 | P14: COUNTY: CLARK
A15: SUBTOTAL | N15: EMPLOYEE | O15: OFFICE | P15: TOTAL
A16: PARKING | B16: 0 | H16: COMMENTS: | N16: 52.06 | O16: 65.33 | P16: 93.33
A17: ADD 6% FOR ADDITIONAL COSTS | B17: 0
A18: GRAND TOTAL | B18: =SUM(B10:B17) -> 0
A20: \/ - MORE FLOORS - \/
A22: COST ESTIMATE | B22: COST | C22: Cost Per Man Hr | D22: Total Hours | E22: Work Day Hours | F22: Total Workers Needed
A23: CLEANING | B23: 0 | C23: 104.5 | D23: =+B23/C23 -> 0 | E23: 9 | F23: =+D23/E23 -> 0
A24: WINDOW WASHING | B24: 0 | C24: 104.5 | D24: =+B24/C24 -> 0 | E24: 9 | F24: =+D24/E24 -> 0
A25: WAXING | B25: 0 | C25: 104.5 | D25: =+B25/C25 -> 0 | E25: 9 | F25: =+D25/E25 -> 0
A26: TRAVEL | B26: 0
A27: LIFT | B27: 0
A28: SUBTOTAL
A29: PARKING | B29: 0
A30: ADD 6% FOR ADDITIONAL COSTS | B30: 0
A31: GRAND TOTAL | B31: =SUM(B23:B30) -> 0
A33: COST ESTIMATE | B33: COST | C33: Cost Per Man Hr | D33: Total Hours | E33: Work Day Hours | F33: Total Workers Needed
A34: CLEANING | B34: 0 | C34: 104.5 | D34: =+B34/C34 -> 0 | E34: 9 | F34: =+D34/E34 -> 0
A35: WINDOW WASHING | B35: 0 | C35: 104.5 | D35: =+B35/C35 -> 0 | E35: 9 | F35: =+D35/E35 -> 0
A36: WAXING | B36: 0 | C36: 104.5 | D36: =+B36/C36 -> 0 | E36: 9 | F36: =+D36/E36 -> 0
A37: TRAVEL | B37: 0
A38: LIFT | B38: 0
A39: SUBTOTAL
A40: PARKING | B40: 0
A41: ADD 6% FOR ADDITIONAL COSTS | B41: 0
A42: GRAND TOTAL | B42: =SUM(B34:B41) -> 0
A44: COST ESTIMATE | B44: COST | C44: Cost Per Man Hr | D44: Total Hours | E44: Work Day Hours | F44: Total Workers Needed
A45: CLEANING | B45: 0 | C45: 104.5 | D45: =+B45/C45 -> 0 | E45: 9 | F45: =+D45/E45 -> 0
A46: WINDOW WASHING | B46: 0 | C46: 104.5 | D46: =+B46/C46 -> 0 | E46: 9 | F46: =+D46/E46 -> 0
A47: WAXING | B47: 0 | C47: 104.5 | D47: =+B47/C47 -> 0 | E47: 9 | F47: =+D47/E47 -> 0
A48: TRAVEL | B48: 0
A49: LIFT | B49: 0
A50: SUBTOTAL
A51: PARKING | B51: 0
A52: ADD 6% FOR ADDITIONAL COSTS | B52: 0
A53: GRAND TOTAL | B53: =SUM(B45:B52) -> 0
A55: COST ESTIMATE | B55: COST | C55: Cost Per Man Hr | D55: Total Hours | E55: Work Day Hours | F55: Total Workers Needed
A56: CLEANING | B56: 0 | C56: 104.5 | D56: =+B56/C56 -> 0 | E56: 9 | F56: =+D56/E56 -> 0
A57: WINDOW WASHING | B57: 0 | C57: 104.5 | D57: =+B57/C57 -> 0 | E57: 9 | F57: =+D57/E57 -> 0
A58: WAXING | B58: 0 | C58: 104.5 | D58: =+B58/C58 -> 0 | E58: 9 | F58: =+D58/E58 -> 0
A59: TRAVEL | B59: 0
A60: LIFT | B60: 0
A61: SUBTOTAL
A62: PARKING | B62: 0
A63: ADD 6% FOR ADDITIONAL COSTS | B63: 0
A64: GRAND TOTAL | B64: =SUM(B56:B63) -> 0
A72: REALITY ESTIMATION
B73: Total SQFT
D74: Work Day Hours | E74: Total hours | F74: Price /hour | G74: Total cost | H74: SQFT PRICE
D75: 9 | E75: =+B76*B77*D75 -> 9 | F75: 104.5 | G75: =+E75*F75 -> 940.5 | H75: =+G75/B74 -> #DIV/0!
A76: Can We Do The Project In X Days -------->>>>>>>>>>> | B76: 1 | C76: DAYS
A77: Can We Do The Project With X Workers -------->>>>> | B77: 1 | C77: WORKERS
A84: WINDOWS | B84: Units
A85: Window Count | C85: 28.5 | D85: =+B85*C85 -> 0
A88: FLOOR WAXING | B88: SqFt
A89: FLOOR | C89: 1.5 | D89: =+B89*C89 -> 0
A91: CARPET - 1st FLOOR ($175 MINIMUM) | B91: SqFt
A92: FLOOR | C92: 0.2 | D92: =+B92*C92 -> 0
A95: AUTOSCRUB FLOORS | B95: SqFt
A96: FLOOR | C96: 0.25 | D96: =+B96*C96 -> 0
A98: CARPET CLEANING | B98: SqFt
A99: FLOOR | C99: 0.81 | D99: =+B99*C99 -> 0
A102: TRAVEL | B102: Workers | C102: Hours | D102: Cost | E102: Days | F102: Total:
A103: Travel | D103: 15 | F103: =+B103*C103*D103*E103 -> 0
A104: Hotel | D104: 115 | F104: =+B104*C104*D104*E104 -> 0
A105: PARKING | D105: 50 | F105: =+B105*C105*D105*E105 -> 0

Sheet INFO SHEET
A2: Clean World Maintenance
A3: (360) 256-9250 - (800) 643-5850 - eburris@cwminc.com
B4: OR Property Services Contractor #61100 | E4: WA Contractor License: CC CLEANMI752JJ
B5: OMWBE Certification Number: | E5: W2F0026094
B6: 19312 NE 58th St. | E6: Vancouver, WA 98682
B7: =INPUT!B9 -> Project : | E7: =INPUT!E9 -> Date :
B8: =INPUT!B10 -> 0 | E8: =INPUT!E10 -> 42874
B9: =INPUT!B11 -> Company | E9: =INPUT!E11 -> Office Phone
B10: =INPUT!B12 -> 0 | E10: =INPUT!E12 -> 0
B11: =INPUT!B13 -> Street: | E11: =INPUT!E13 -> Contact:
B12: =INPUT!B14 -> 0 | E12: =INPUT!E14 -> 0
B13: =INPUT!B15 -> City & State | E13: =INPUT!E15 -> Cell Phone
B14: =INPUT!B16 -> 0 | E14: =INPUT!E16 -> 0
B16: =INPUT!B18 -> Notes:
B17: =INPUT!B19 -> We propose to furnish all materials and perform labor necessary to complete
B18: =INPUT!B20 -> the following cleaning service at Prevailing Wage rate:
B19: Acknowledge Addendum(s) -
B21: =INPUT!B23 -> Final Cleaning Cost: $
B22: =INPUT!B24 -> This would be the cleaning of walls, doors, doorframes, lights, fixtures, vacuum,
B23: =INPUT!B25 -> switches, plug plates, baseboards, cabinets, restrooms, sweep and mop.
B24: Cleaning of all windows and frames, as well as all relites in the work area.
B25: High dusting and aerial lifts not included.
B27: =INPUT!B26 -> _ Final Cleaning Cost: $
B28: =INPUT!B27 -> This would be the cleaning of walls, doors, doorframes, lights, fixtures, vacuum,
B29: =INPUT!B28 -> switches, plug plates, baseboards, cabinets, restrooms, sweep and mop.
B30: Cleaning of all windows and frames, as well as all relites in the work area.
B31: High dusting and aerial lifts not included.
B33: =INPUT!B29 -> Floor Cleaning Cost: $
B34: =INPUT!B30 -> Removal of factory finish and applying 3 coats of wax to VCT flooring.
B36: This would be the cleaning of walls, doors, doorframes, lights, fixtures, vacuum,
B37: switches, plug plates, baseboards, cabinets, restrooms, sweep and mop.
B38: Cleaning of all windows and frames, as well as all relites in the work area.
B39: High dusting and aerial lifts not included.
B41: General Cleaning Cost: $ 39.00 per worker hour
B42: General cleanup of work area. Following directions provided by supervisor.
B44: Elevator Driver Cost: $ 39.00 per worker hour
B45: English and Spanish speaking elevator driver. Normal work day (M-F)
B48: Final Cleaning pricing is based on one standard post-construction final clean prior to
B49: Substantial Completion. Any additional cleaning required due to inspections,
B50: punch work, phased turnover, trade access, or post-clean re-soiling per drawings,
B51: specifications, or addenda will be treated as additional service.
... B59: Date of Acceptance ______________ Signature________________
